pcapy.cp310-win_amd64.pyd
pcapy_ng_win_amd64-1.0.4.data/data/share/doc/pcapy-ng-win-amd64/LICENSE
pcapy_ng_win_amd64-1.0.4.data/data/share/doc/pcapy-ng-win-amd64/README
pcapy_ng_win_amd64-1.0.4.data/data/share/doc/pcapy-ng-win-amd64/pcapy.html
pcapy_ng_win_amd64-1.0.4.data/data/share/doc/pcapy-ng-win-amd64/tests/96pings.pcap
pcapy_ng_win_amd64-1.0.4.data/data/share/doc/pcapy-ng-win-amd64/tests/pcapytests.py
pcapy_ng_win_amd64-1.0.4.dist-info/LICENSE
pcapy_ng_win_amd64-1.0.4.dist-info/METADATA
pcapy_ng_win_amd64-1.0.4.dist-info/WHEEL
pcapy_ng_win_amd64-1.0.4.dist-info/top_level.txt
pcapy_ng_win_amd64-1.0.4.dist-info/RECORD
