Metadata-Version: 2.1
Name: pcapy-ng-win-amd64
Version: 1.0.4
Summary: Python pcap extension (pre-built for win-amd64)
Home-page: https://github.com/stamparm/pcapy-ng/
Author: Miroslav Stampar
Author-email: miroslav@sqlmap.org
Maintainer: Kevin Ruff
Maintainer-email: ruff.kevin@outlook.com
License: Apache
Platform: Unix
Platform: Windows
Classifier: Development Status :: 5 - Production/Stable
Classifier: Environment :: Win32 (MS Windows)
Classifier: Intended Audience :: Developers
Classifier: License :: OSI Approved :: Apache Software License
Classifier: Operating System :: Microsoft :: Windows
Classifier: Programming Language :: Python :: 3
Classifier: Topic :: Internet
Classifier: Topic :: Utilities
License-File: LICENSE
